jupyterlab_viz_krunk/__init__.py
jupyterlab_viz_krunk/_version.py
jupyterlab_viz_krunk-0.1.6.data/data/share/jupyter/labextensions/jupyterlab-viz-krunk/build_log.json
jupyterlab_viz_krunk-0.1.6.data/data/share/jupyter/labextensions/jupyterlab-viz-krunk/package.json
jupyterlab_viz_krunk-0.1.6.data/data/share/jupyter/labextensions/jupyterlab-viz-krunk/static/lib_index_js.cc107bf6084b0fe5520e.js
jupyterlab_viz_krunk-0.1.6.data/data/share/jupyter/labextensions/jupyterlab-viz-krunk/static/lib_index_js.cc107bf6084b0fe5520e.js.map
jupyterlab_viz_krunk-0.1.6.data/data/share/jupyter/labextensions/jupyterlab-viz-krunk/static/remoteEntry.02407db21675e9ab8821.js
jupyterlab_viz_krunk-0.1.6.data/data/share/jupyter/labextensions/jupyterlab-viz-krunk/static/remoteEntry.02407db21675e9ab8821.js.map
jupyterlab_viz_krunk-0.1.6.data/data/share/jupyter/labextensions/jupyterlab-viz-krunk/static/remoteEntry.7db13e487a33ecf48fd2.js.map
jupyterlab_viz_krunk-0.1.6.data/data/share/jupyter/labextensions/jupyterlab-viz-krunk/static/style.js
jupyterlab_viz_krunk-0.1.6.data/data/share/jupyter/labextensions/jupyterlab-viz-krunk/static/style_index_js.50c8473890e31780716c.js
jupyterlab_viz_krunk-0.1.6.data/data/share/jupyter/labextensions/jupyterlab-viz-krunk/static/style_index_js.50c8473890e31780716c.js.map
jupyterlab_viz_krunk-0.1.6.data/data/share/jupyter/labextensions/jupyterlab-viz-krunk/static/style_index_js.f9342a69d1ea80ca837b.js
jupyterlab_viz_krunk-0.1.6.data/data/share/jupyter/labextensions/jupyterlab-viz-krunk/static/style_index_js.f9342a69d1ea80ca837b.js.map
jupyterlab_viz_krunk-0.1.6.data/data/share/jupyter/labextensions/jupyterlab-viz-krunk/install.json
jupyterlab_viz_krunk-0.1.6.dist-info/METADATA
jupyterlab_viz_krunk-0.1.6.dist-info/WHEEL
jupyterlab_viz_krunk-0.1.6.dist-info/licenses/LICENSE
jupyterlab_viz_krunk-0.1.6.dist-info/RECORD
