Metadata-Version: 2.3
Name: jupyterlab_viz_krunk
Version: 0.1.6
Dynamic: Keywords
Summary: Graphviz markdown support
Project-URL: Homepage, https://github.com/KrunkZhou/jupyterlab-viz-krunk
Project-URL: Bug Tracker, https://github.com/KrunkZhou/jupyterlab-viz-krunk/issues
Project-URL: Repository, https://github.com/KrunkZhou/jupyterlab-viz-krunk.git
Author-email: KrunkZhou <webmaster@krunk.cn>
License: BSD 3-Clause License
License-File: LICENSE
Classifier: Framework :: Jupyter
Classifier: Framework :: Jupyter :: JupyterLab
Classifier: Framework :: Jupyter :: JupyterLab :: 4
Classifier: Framework :: Jupyter :: JupyterLab :: Extensions
Classifier: Framework :: Jupyter :: JupyterLab :: Extensions :: Prebuilt
Classifier: License :: OSI Approved :: BSD License
Classifier: Programming Language :: Python
Classifier: Programming Language :: Python :: 3
Classifier: Programming Language :: Python :: 3.8
Classifier: Programming Language :: Python :: 3.9
Classifier: Programming Language :: Python :: 3.10
Classifier: Programming Language :: Python :: 3.11
Classifier: Programming Language :: Python :: 3.12
Requires-Python: >=3.8
